pydantic_ai_mlx_lm/__init__.py
pydantic_ai_mlx_lm/agent_model.py
pydantic_ai_mlx_lm/model.py
pydantic_ai_mlx_lm/py.typed
pydantic_ai_mlx_lm/response.py
pydantic_ai_mlx_lm/stream.py
pydantic_ai_mlx_lm/utils.py
pydantic_ai_providers/__init__.py
pydantic_ai_providers/lm_studio.py
pydantic_ai_providers/openrouter.py
pydantic_ai_providers/py.typed
pydantic_ai_mlx-0.2.5.dist-info/METADATA
pydantic_ai_mlx-0.2.5.dist-info/WHEEL
pydantic_ai_mlx-0.2.5.dist-info/RECORD
