Metadata-Version: 2.4
Name: pydantic-ai-mlx
Version: 0.2.5
Summary: Run MLX compatible HuggingFace models with Pydantic AI locally
Author-email: Doruk Gezici <doruk@gezici.me>
Requires-Python: >=3.12
Requires-Dist: openai>=1.65.4
Requires-Dist: pydantic-ai-slim>=0.0.36
Provides-Extra: mac
Requires-Dist: mlx-lm>=0.21.5; extra == 'mac'
